turtler/__init__.py
turtler/main.py
turtler-0.0.3.dist-info/LICENSE
turtler-0.0.3.dist-info/METADATA
turtler-0.0.3.dist-info/WHEEL
turtler-0.0.3.dist-info/top_level.txt
turtler-0.0.3.dist-info/RECORD
