Metadata-Version: 2.1
Name: turtler
Version: 0.0.3
Summary: A fun way to get started with graphics and data science in python
Home-page: https://github.com/dehadeaaryan/turtler
Author: Aaryan Dehade
Author-email: dehadeaaryan@gmail.com
Project-URL: Bug Tracker, https://github.com/dehadeaaryan/turtler/issues
Classifier: Programming Language :: Python :: 3
Classifier: License :: OSI Approved :: MIT License
Classifier: Operating System :: OS Independent
Requires-Python: >=3.6
License-File: LICENSE
